keyedtensor/__init__.py
keyedtensor/_keyedsize.py
keyedtensor/_keyedtensor.py
keyedtensor/_registry.py
keyedtensor/_repr_utils.py
keyedtensor/py.typed
keyedtensor-0.3.0.dist-info/AUTHORS.md
keyedtensor-0.3.0.dist-info/LICENSE
keyedtensor-0.3.0.dist-info/METADATA
keyedtensor-0.3.0.dist-info/WHEEL
keyedtensor-0.3.0.dist-info/top_level.txt
keyedtensor-0.3.0.dist-info/RECORD
