Metadata-Version: 2.1
Name: keyedtensor
Version: 0.3.0
Summary: keyed torch tensors
Home-page: https://github.com/leaprovenzano/keyedtensor
Author: Lea Provenzano
Author-email: leaprovenzano@gmail.com
License: MIT license
Keywords: keyedtensor
Platform: UNKNOWN
Classifier: Development Status :: 2 - Pre-Alpha
Classifier: Intended Audience :: Developers
Classifier: License :: OSI Approved :: MIT License
Classifier: Natural Language :: English
Classifier: Programming Language :: Python :: 3
Classifier: Programming Language :: Python :: 3.7
Classifier: Programming Language :: Python :: 3.8
Classifier: Programming Language :: Python :: 3 :: Only
Requires-Dist: collectionish (>=0.3.0)
Requires-Dist: torch
Requires-Dist: typing-extensions ; python_version < "3.8"
Requires-Dist: cached-property ; python_version < "3.8"
